{
    "44963": {
        "Ridge": {
            "score_train": [
                0.8389559984207153,
                0.8352134823799133,
                0.8383675217628479,
                0.8425098657608032,
                0.8349855542182922
            ],
            "score_test": [
                0.8360514044761658,
                0.8507303595542908,
                0.8406895399093628,
                0.8229014277458191,
                0.8534086346626282
            ],
            "t_fit": [
                0.0005029737949371338,
                0.00040158629417419434,
                0.0004491284489631653,
                0.00045334547758102417,
                0.00040067732334136963
            ],
            "t_inference": [
                5.136057734489441e-05,
                4.09446656703949e-05,
                4.289299249649048e-05,
                4.4148415327072144e-05,
                4.116073250770569e-05
            ],
            "hyperparams": [
                {
                    "l2_reg": 0.0005907746115479407
                },
                {
                    "l2_reg": 0.00024491265870832385
                },
                {
                    "l2_reg": 0.0019236831690364882
                },
                {
                    "l2_reg": 0.001141380992493767
                },
                {
                    "l2_reg": 0.002049075083028099
                }
            ]
        }
    }
}