{
    "44964": {
        "RFNN": {
            "score_train": [
                0.41944870352745056,
                0.406697541475296,
                0.4160965085029602,
                0.4072685241699219,
                0.40073534846305847
            ],
            "score_test": [
                0.4210813641548157,
                0.4322507083415985,
                0.4537588655948639,
                0.4541950523853302,
                0.45240524411201477
            ],
            "t_fit": [
                0.1409362033009529,
                0.12688902765512466,
                0.11562348902225494,
                0.09310721606016159,
                0.11429201066493988
            ],
            "t_inference": [
                0.04399696737527847,
                0.038889214396476746,
                0.03579840064048767,
                0.020295865833759308,
                0.03480662405490875
            ],
            "hyperparams": [
                {
                    "n_layers": 0,
                    "in_dim": 81,
                    "out_dim": 1,
                    "upscale_type": "SWIM",
                    "activation": "tanh",
                    "use_batchnorm": false,
                    "l2_reg": 0.00018586367583329157,
                    "hidden_dim": 504,
                    "SWIM_scale": 1.319441850928509
                },
                {
                    "n_layers": 0,
                    "in_dim": 81,
                    "out_dim": 1,
                    "upscale_type": "SWIM",
                    "activation": "tanh",
                    "use_batchnorm": false,
                    "l2_reg": 5.275567094476528e-05,
                    "hidden_dim": 511,
                    "SWIM_scale": 1.2382300164823372
                },
                {
                    "n_layers": 0,
                    "in_dim": 81,
                    "out_dim": 1,
                    "upscale_type": "SWIM",
                    "activation": "tanh",
                    "use_batchnorm": false,
                    "l2_reg": 0.00032015608972860973,
                    "hidden_dim": 488,
                    "SWIM_scale": 1.5178112023639916
                },
                {
                    "n_layers": 0,
                    "in_dim": 81,
                    "out_dim": 1,
                    "upscale_type": "SWIM",
                    "activation": "tanh",
                    "use_batchnorm": false,
                    "l2_reg": 0.00030894649160662937,
                    "hidden_dim": 509,
                    "SWIM_scale": 1.6563164410609161
                },
                {
                    "n_layers": 0,
                    "in_dim": 81,
                    "out_dim": 1,
                    "upscale_type": "SWIM",
                    "activation": "tanh",
                    "use_batchnorm": false,
                    "l2_reg": 3.903206254750543e-05,
                    "hidden_dim": 471,
                    "SWIM_scale": 1.4617339186712361
                }
            ]
        }
    }
}