{
    "45402": {
        "End2End_cpu": {
            "score_train": [
                0.3402329981327057,
                0.37144166231155396,
                0.37985846400260925,
                0.37310391664505005,
                0.35410767793655396
            ],
            "score_test": [
                0.5060316920280457,
                0.5002599358558655,
                0.46453842520713806,
                0.4526434540748596,
                0.45030999183654785
            ],
            "t_fit": [
                28.63387841358781,
                10.52218110114336,
                35.903589352965355,
                28.157866593450308,
                33.968309845775366
            ],
            "t_inference": [
                0.17002640664577484,
                0.04606811702251434,
                0.25717033073306084,
                0.2294665277004242,
                0.3048565164208412
            ],
            "hyperparams": [
                {
                    "in_dim": 6,
                    "out_dim": 1,
                    "loss": "mse",
                    "bottleneck_dim": 512,
                    "n_blocks": 6,
                    "hidden_dim": 73,
                    "lr": 0.0008542471950914868,
                    "end_lr_factor": 0.018135748426737406,
                    "n_epochs": 46,
                    "weight_decay": 3.563611739312604e-05,
                    "batch_size": 128
                },
                {
                    "in_dim": 6,
                    "out_dim": 1,
                    "loss": "mse",
                    "bottleneck_dim": 512,
                    "n_blocks": 2,
                    "hidden_dim": 80,
                    "lr": 0.00041594685160172484,
                    "end_lr_factor": 0.024521937023101157,
                    "n_epochs": 40,
                    "weight_decay": 0.0002495409969243108,
                    "batch_size": 128
                },
                {
                    "in_dim": 6,
                    "out_dim": 1,
                    "loss": "mse",
                    "bottleneck_dim": 512,
                    "n_blocks": 3,
                    "hidden_dim": 348,
                    "lr": 0.0006967041294212539,
                    "end_lr_factor": 0.016149253455077398,
                    "n_epochs": 43,
                    "weight_decay": 0.00012203580933545519,
                    "batch_size": 128
                },
                {
                    "in_dim": 6,
                    "out_dim": 1,
                    "loss": "mse",
                    "bottleneck_dim": 512,
                    "n_blocks": 2,
                    "hidden_dim": 363,
                    "lr": 0.00013902873090939317,
                    "end_lr_factor": 0.01345027038168267,
                    "n_epochs": 39,
                    "weight_decay": 0.00010903351930082162,
                    "batch_size": 128
                },
                {
                    "in_dim": 6,
                    "out_dim": 1,
                    "loss": "mse",
                    "bottleneck_dim": 512,
                    "n_blocks": 5,
                    "hidden_dim": 265,
                    "lr": 0.00044394282930128754,
                    "end_lr_factor": 0.014784681979168851,
                    "n_epochs": 39,
                    "weight_decay": 3.9321396937219185e-06,
                    "batch_size": 128
                }
            ]
        }
    }
}