{
    "11": {
        "XGBoostClassifier": {
            "score_train": [
                -0.9819999933242798,
                -0.9760000109672546,
                -0.9200000166893005,
                -0.9860000014305115,
                -0.9319999814033508
            ],
            "score_test": [
                -0.9279999732971191,
                -0.9760000109672546,
                -0.9279999732971191,
                -0.9440000057220459,
                -0.8799999952316284
            ],
            "t_fit": [
                0.22978787124156952,
                0.199029378592968,
                0.21586062014102936,
                0.37453410029411316,
                0.33789700269699097
            ],
            "t_inference": [
                0.010939821600914001,
                0.009090766310691833,
                0.010132946074008942,
                0.01640459895133972,
                0.015109196305274963
            ],
            "hyperparams": [
                {
                    "objective": "binary:logistic",
                    "num_class": 3,
                    "alpha": 0.00037633805048258744,
                    "lambda": 1.3587124445598417,
                    "learning_rate": 0.47639261551850737,
                    "n_estimators": 673,
                    "max_depth": 1
                },
                {
                    "objective": "binary:logistic",
                    "num_class": 3,
                    "alpha": 1.6193147865719047e-05,
                    "lambda": 4.553224389882664,
                    "learning_rate": 0.44903031736946997,
                    "n_estimators": 583,
                    "max_depth": 1
                },
                {
                    "objective": "binary:logistic",
                    "num_class": 3,
                    "alpha": 9.005733556091367e-05,
                    "lambda": 0.2646211799417548,
                    "learning_rate": 0.053346503227960466,
                    "n_estimators": 633,
                    "max_depth": 1
                },
                {
                    "objective": "binary:logistic",
                    "num_class": 3,
                    "alpha": 4.324433741408465e-05,
                    "lambda": 0.41655214884316777,
                    "learning_rate": 0.36972851589613603,
                    "n_estimators": 1000,
                    "max_depth": 1
                },
                {
                    "objective": "binary:logistic",
                    "num_class": 3,
                    "alpha": 7.230512360748786e-05,
                    "lambda": 0.4920529633243035,
                    "learning_rate": 0.05224888160478117,
                    "n_estimators": 964,
                    "max_depth": 1
                }
            ]
        }
    }
}