{
    "1510": {
        "LogisticRegression": {
            "score_train": [
                -0.9890109896659851,
                -0.9890109896659851,
                -0.9890109896659851,
                -0.9846153855323792,
                -0.9912280440330505
            ],
            "score_test": [
                -0.9736841917037964,
                -0.9824561476707458,
                -0.9824561476707458,
                -0.9736841917037964,
                -0.9734513163566589
            ],
            "t_fit": [
                0.023606449365615845,
                0.02156130224466324,
                0.022748034447431564,
                0.022338014096021652,
                0.020053181797266006
            ],
            "t_inference": [
                0.00010726600885391235,
                9.173154830932617e-05,
                0.00011287257075309753,
                0.00010578334331512451,
                8.931756019592285e-05
            ],
            "hyperparams": [
                {
                    "n_classes": 2,
                    "l2_lambda": 0.001205328285911237
                },
                {
                    "n_classes": 2,
                    "l2_lambda": 0.0017670169402947942
                },
                {
                    "n_classes": 2,
                    "l2_lambda": 0.0017670169402947942
                },
                {
                    "n_classes": 2,
                    "l2_lambda": 0.002116241488455615
                },
                {
                    "n_classes": 2,
                    "l2_lambda": 0.002508315358664581
                }
            ]
        }
    }
}