{
    "1486": {
        "RFRBoost_ID_batchnormFalse": {
            "score_train": [
                -0.9745000004768372,
                -0.9794999957084656,
                -0.9735000133514404,
                -0.9754999876022339,
                -0.9570000171661377
            ],
            "score_test": [
                -0.9480000138282776,
                -0.9459999799728394,
                -0.9539999961853027,
                -0.9509999752044678,
                -0.9480000138282776
            ],
            "t_fit": [
                2.8070836886763573,
                5.876566959545016,
                0.588385347276926,
                5.329301588237286,
                2.350370790809393
            ],
            "t_inference": [
                0.4670638684183359,
                1.264965683221817,
                0.12044681049883366,
                1.1633151229470968,
                0.5135812945663929
            ],
            "hyperparams": [
                {
                    "in_dim": 174,
                    "n_classes": 2,
                    "feature_type": "SWIM",
                    "upscale_type": "identity",
                    "randfeat_xt_dim": 512,
                    "randfeat_x0_dim": 512,
                    "activation": "tanh",
                    "use_batchnorm": false,
                    "do_linesearch": true,
                    "add_features": false,
                    "n_layers": 3,
                    "hidden_dim": 174,
                    "l2_cls": 0.0004424849865395578,
                    "l2_ghat": 0.000682850614970127,
                    "boost_lr": 0.20324817001253365,
                    "SWIM_scale": 1.3562321060870255
                },
                {
                    "in_dim": 174,
                    "n_classes": 2,
                    "feature_type": "SWIM",
                    "upscale_type": "identity",
                    "randfeat_xt_dim": 512,
                    "randfeat_x0_dim": 512,
                    "activation": "tanh",
                    "use_batchnorm": false,
                    "do_linesearch": true,
                    "add_features": false,
                    "n_layers": 9,
                    "hidden_dim": 174,
                    "l2_cls": 0.007136748420762265,
                    "l2_ghat": 0.0003573456941891913,
                    "boost_lr": 0.10696268887352989,
                    "SWIM_scale": 1.1729327743820337
                },
                {
                    "in_dim": 174,
                    "n_classes": 2,
                    "feature_type": "SWIM",
                    "upscale_type": "identity",
                    "randfeat_xt_dim": 512,
                    "randfeat_x0_dim": 512,
                    "activation": "tanh",
                    "use_batchnorm": false,
                    "do_linesearch": true,
                    "add_features": false,
                    "n_layers": 1,
                    "hidden_dim": 174,
                    "l2_cls": 0.005495578361185745,
                    "l2_ghat": 1.5028444673345625e-05,
                    "boost_lr": 0.4781757171166336,
                    "SWIM_scale": 1.1814150486514974
                },
                {
                    "in_dim": 174,
                    "n_classes": 2,
                    "feature_type": "SWIM",
                    "upscale_type": "identity",
                    "randfeat_xt_dim": 512,
                    "randfeat_x0_dim": 512,
                    "activation": "tanh",
                    "use_batchnorm": false,
                    "do_linesearch": true,
                    "add_features": false,
                    "n_layers": 7,
                    "hidden_dim": 174,
                    "l2_cls": 0.002092785279620438,
                    "l2_ghat": 0.002503299659387049,
                    "boost_lr": 0.12354700063247488,
                    "SWIM_scale": 1.7731704605726597
                },
                {
                    "in_dim": 174,
                    "n_classes": 2,
                    "feature_type": "SWIM",
                    "upscale_type": "identity",
                    "randfeat_xt_dim": 512,
                    "randfeat_x0_dim": 512,
                    "activation": "tanh",
                    "use_batchnorm": false,
                    "do_linesearch": true,
                    "add_features": false,
                    "n_layers": 3,
                    "hidden_dim": 174,
                    "l2_cls": 0.0028530514879141038,
                    "l2_ghat": 0.118636148389586,
                    "boost_lr": 0.7335318186157417,
                    "SWIM_scale": 1.1449334072360213
                }
            ]
        }
    }
}