{
    "37": {
        "XGBoostClassifier": {
            "score_train": [
                -0.7899022698402405,
                -0.7980455756187439,
                -1.0,
                -0.8162601590156555,
                -0.8227642178535461
            ],
            "score_test": [
                -0.7272727489471436,
                -0.8181818127632141,
                -0.7597402334213257,
                -0.7254902124404907,
                -0.7777777910232544
            ],
            "t_fit": [
                0.042348794639110565,
                0.11881975084543228,
                0.3592115268111229,
                0.044185981154441833,
                0.07615439593791962
            ],
            "t_inference": [
                0.0035894662141799927,
                0.005590818822383881,
                0.016663506627082825,
                0.003585115075111389,
                0.005028985440731049
            ],
            "hyperparams": [
                {
                    "objective": "multi:softmax",
                    "num_class": 2,
                    "alpha": 0.00021831996433707964,
                    "lambda": 71.10481724190025,
                    "learning_rate": 0.24670318094713298,
                    "n_estimators": 103,
                    "max_depth": 1
                },
                {
                    "objective": "multi:softmax",
                    "num_class": 2,
                    "alpha": 0.001549514398058318,
                    "lambda": 0.018250345339827646,
                    "learning_rate": 0.09842075328555466,
                    "n_estimators": 329,
                    "max_depth": 1
                },
                {
                    "objective": "multi:softmax",
                    "num_class": 2,
                    "alpha": 0.0001747265778833905,
                    "lambda": 0.027325370503493446,
                    "learning_rate": 0.03720130091634261,
                    "n_estimators": 182,
                    "max_depth": 6
                },
                {
                    "objective": "multi:softmax",
                    "num_class": 2,
                    "alpha": 0.00024297372197656846,
                    "lambda": 0.008244168763292908,
                    "learning_rate": 0.06762644399011984,
                    "n_estimators": 106,
                    "max_depth": 1
                },
                {
                    "objective": "multi:softmax",
                    "num_class": 2,
                    "alpha": 1.7440895508128293e-05,
                    "lambda": 0.36772612948775374,
                    "learning_rate": 0.04721557377291228,
                    "n_estimators": 136,
                    "max_depth": 2
                }
            ]
        }
    }
}