{
    "6332": {
        "End2End_cpu": {
            "score_train": [
                -1.0,
                -1.0,
                -1.0,
                -1.0,
                -1.0
            ],
            "score_test": [
                -0.7777777910232544,
                -0.7685185074806213,
                -0.7962962985038757,
                -0.7777777910232544,
                -0.8333333134651184
            ],
            "t_fit": [
                5.296218439936638,
                3.7473216131329536,
                12.782746113836765,
                9.706179827451706,
                9.667259521782398
            ],
            "t_inference": [
                0.03189382702112198,
                0.022774167358875275,
                0.1350027099251747,
                0.09017591923475266,
                0.0929657444357872
            ],
            "hyperparams": [
                {
                    "in_dim": 173,
                    "out_dim": 1,
                    "loss": "bce",
                    "bottleneck_dim": 512,
                    "n_blocks": 8,
                    "hidden_dim": 80,
                    "lr": 0.017026059090293272,
                    "end_lr_factor": 0.0171775708475228,
                    "n_epochs": 50,
                    "weight_decay": 0.0003855118730919056,
                    "batch_size": 128
                },
                {
                    "in_dim": 173,
                    "out_dim": 1,
                    "loss": "bce",
                    "bottleneck_dim": 512,
                    "n_blocks": 4,
                    "hidden_dim": 124,
                    "lr": 0.004414917632967877,
                    "end_lr_factor": 0.0792494537659611,
                    "n_epochs": 47,
                    "weight_decay": 8.504952099766943e-06,
                    "batch_size": 128
                },
                {
                    "in_dim": 173,
                    "out_dim": 1,
                    "loss": "bce",
                    "bottleneck_dim": 512,
                    "n_blocks": 10,
                    "hidden_dim": 303,
                    "lr": 0.009709920722586146,
                    "end_lr_factor": 0.012546245869204034,
                    "n_epochs": 38,
                    "weight_decay": 0.00015597353711791897,
                    "batch_size": 128
                },
                {
                    "in_dim": 173,
                    "out_dim": 1,
                    "loss": "bce",
                    "bottleneck_dim": 512,
                    "n_blocks": 5,
                    "hidden_dim": 458,
                    "lr": 0.005189852826332061,
                    "end_lr_factor": 0.016845191559316238,
                    "n_epochs": 40,
                    "weight_decay": 0.0003015513579532083,
                    "batch_size": 128
                },
                {
                    "in_dim": 173,
                    "out_dim": 1,
                    "loss": "bce",
                    "bottleneck_dim": 512,
                    "n_blocks": 6,
                    "hidden_dim": 397,
                    "lr": 0.004665930127118084,
                    "end_lr_factor": 0.015618748031782703,
                    "n_epochs": 39,
                    "weight_decay": 0.0003076399456423649,
                    "batch_size": 128
                }
            ]
        }
    }
}